infoservice/__init__.py
infoservice/infoservice.py
homehub_info_service-1.0.0.dist-info/METADATA
homehub_info_service-1.0.0.dist-info/WHEEL
homehub_info_service-1.0.0.dist-info/top_level.txt
homehub_info_service-1.0.0.dist-info/RECORD
